CHANGELOG.md
README.md
py_meta_utils/__init__.py
py_meta_utils/py.typed
py_meta_utils-0.8.0.dist-info/LICENSE
py_meta_utils-0.8.0.dist-info/METADATA
py_meta_utils-0.8.0.dist-info/WHEEL
py_meta_utils-0.8.0.dist-info/RECORD
