Metadata-Version: 2.1
Name: py-meta-utils
Version: 0.8.0
Summary: Metaclass and metaprogramming utilities for Python
Author: Brian Cappello
Author-email: briancappello@gmail.com
Requires-Python: >=3.8,<4.0
Classifier: Programming Language :: Python :: 3
Classifier: Programming Language :: Python :: 3.8
Classifier: Programming Language :: Python :: 3.9
Classifier: Programming Language :: Python :: 3.10
Classifier: Programming Language :: Python :: 3.11
Classifier: Programming Language :: Python :: 3.12
